poppdf/__init__.py
poppdf/__version__.py
poppdf/alto.py
poppdf/alto_xml.py
poppdf/common.py
poppdf/exceptions.py
poppdf/generators.py
poppdf/ocd.py
poppdf/ocr.py
poppdf/parsers.py
poppdf/pdf.py
poppdf/pdfDocument.py
poppdf/poppler.py
poppdf/utils.py
poppdf-0.17.8.dist-info/LICENSE
poppdf-0.17.8.dist-info/METADATA
poppdf-0.17.8.dist-info/WHEEL
poppdf-0.17.8.dist-info/top_level.txt
poppdf-0.17.8.dist-info/RECORD
