Metadata-Version: 2.1
Name: poppdf
Version: 0.17.8
Summary: A wrapper around the poppler's and pdftoimage, pdftphtml and pdftotext command line tools to extract informaton from pdf
Home-page: UNKNOWN
Author: Mohamed Ben Haddou
Author-email: haddomoh@gmail.com
License: MIT
Keywords: pdf image png jpeg jpg convert text xml
Platform: UNKNOWN
Classifier: Development Status :: 5 - Production/Stable
Classifier: Intended Audience :: Developers
Classifier: License :: OSI Approved :: MIT License
Classifier: Programming Language :: Python :: 3
Classifier: Programming Language :: Python :: 3.5
Classifier: Programming Language :: Python :: 3.6
Classifier: Programming Language :: Python :: 3.7
Classifier: Programming Language :: Python :: 3.8
License-File: LICENSE
Requires-Dist: pillow
Requires-Dist: kdmt
